maj7/__init__.py
maj7/executer.py
maj7/lexer.py
maj7/maj7.py
maj7/parser.py
maj7/utils.py
maj7-0.9.2.data/scripts/maj7.py
maj7-0.9.2.dist-info/LICENSE
maj7-0.9.2.dist-info/METADATA
maj7-0.9.2.dist-info/WHEEL
maj7-0.9.2.dist-info/entry_points.txt
maj7-0.9.2.dist-info/top_level.txt
maj7-0.9.2.dist-info/RECORD
